IMDLBenCo/__init__.py
IMDLBenCo/build_functions.py
IMDLBenCo/cli.py
IMDLBenCo/registry.py
IMDLBenCo/version.py
IMDLBenCo/cli_funcs/__init__.py
IMDLBenCo/cli_funcs/cli_env.py
IMDLBenCo/cli_funcs/cli_init.py
IMDLBenCo/cli_funcs/copy_funcs.py
IMDLBenCo/datasets/__init__.py
IMDLBenCo/datasets/abstract_dataset.py
IMDLBenCo/datasets/balanced_dataset.py
IMDLBenCo/datasets/dummy_dataset.py
IMDLBenCo/datasets/iml_datasets.py
IMDLBenCo/datasets/jpeg_dataset_deprecated.py
IMDLBenCo/datasets/utils.py
IMDLBenCo/evaluation/AUC.py
IMDLBenCo/evaluation/Accuracy.py
IMDLBenCo/evaluation/F1.py
IMDLBenCo/evaluation/IOU.py
IMDLBenCo/evaluation/__init__.py
IMDLBenCo/evaluation/abstract_class.py
IMDLBenCo/evaluation/temp.py
IMDLBenCo/evaluation/gradcam/activations_and_gradients_hack.py
IMDLBenCo/evaluation/gradcam/base_cam_hack.py
IMDLBenCo/evaluation/gradcam/grad_cam_hack.py
IMDLBenCo/evaluation/gradcam/grad_camera_visualize.py
IMDLBenCo/model_zoo/README.md
IMDLBenCo/model_zoo/__init__.py
IMDLBenCo/model_zoo/cat_net/README.md
IMDLBenCo/model_zoo/cat_net/__init__.py
IMDLBenCo/model_zoo/cat_net/cat_net.py
IMDLBenCo/model_zoo/cat_net/cat_net_post_function.py
IMDLBenCo/model_zoo/cat_net/network_CAT.py
IMDLBenCo/model_zoo/iml_vit/README.md
IMDLBenCo/model_zoo/iml_vit/__init__.py
IMDLBenCo/model_zoo/iml_vit/decoderhead.py
IMDLBenCo/model_zoo/iml_vit/iml_vit.py
IMDLBenCo/model_zoo/iml_vit/windowed_attention_vit.py
IMDLBenCo/model_zoo/mantra_net/README.md
IMDLBenCo/model_zoo/mantra_net/__init__.py
IMDLBenCo/model_zoo/mantra_net/mantranet.py
IMDLBenCo/model_zoo/mantra_net/modify_weights.py
IMDLBenCo/model_zoo/mesorch/README.md
IMDLBenCo/model_zoo/mesorch/__init__.py
IMDLBenCo/model_zoo/mesorch/mesorch.py
IMDLBenCo/model_zoo/mesorch/extractor/__init__.py
IMDLBenCo/model_zoo/mesorch/extractor/high_frequency_feature_extraction.py
IMDLBenCo/model_zoo/mesorch/extractor/low_frequency_feature_extraction.py
IMDLBenCo/model_zoo/mvss_net/README.md
IMDLBenCo/model_zoo/mvss_net/__init__.py
imdlbenco-0.1.42.dist-info/licenses/LICENSE
imdlbenco-0.1.42.dist-info/METADATA
imdlbenco-0.1.42.dist-info/WHEEL
imdlbenco-0.1.42.dist-info/entry_points.txt
imdlbenco-0.1.42.dist-info/top_level.txt
imdlbenco-0.1.42.dist-info/RECORD
