Metadata-Version: 2.4
Name: imdlbenco
Version: 0.1.42
Summary: A comprehensive benchmark and code base for Image manipulation and localization.
Author-email: Xiaochen Ma <xiaochen.ma.cs@gmail.com>
License: CC-BY-4.0
Project-URL: Github, https://github.com/scu-zjz/IMDLBenCo/
Project-URL: Documentation, https://github.com/scu-zjz/IMDLBenCo-doc
Project-URL: Bug Reports, https://github.com/scu-zjz/IMDLBenCo/issues
Keywords: AI,artificial intelligence,image forensics,image manipulation localization,image manipulation detection
Classifier: Development Status :: 3 - Alpha
Classifier: Intended Audience :: Developers
Classifier: Intended Audience :: Science/Research
Classifier: Topic :: Security
Classifier: Topic :: Scientific/Engineering :: Artificial Intelligence
Classifier: License :: Free For Educational Use
Classifier: Programming Language :: Python :: 3
Classifier: Programming Language :: Python :: 3.7
Classifier: Programming Language :: Python :: 3.8
Classifier: Programming Language :: Python :: 3.9
Classifier: Programming Language :: Python :: 3.10
Classifier: Programming Language :: Python :: 3 :: Only
Requires-Python: <4,>=3.7
License-File: LICENSE
Requires-Dist: rich
Requires-Dist: fvcore
Requires-Dist: albumentations==1.3.0
Requires-Dist: matplotlib
Requires-Dist: numpy<2
Requires-Dist: scikit_learn
Requires-Dist: timm
Requires-Dist: fvcore
Requires-Dist: tensorboard
Requires-Dist: grad_cam
Requires-Dist: ttach
Requires-Dist: appdirs
Requires-Dist: colorama
Dynamic: license-file
